CHANGELOG
LICENSE.txt
MANIFEST.in
README.rst
setup.py
clark/__init__.py
clark/super_argparser.py
clark/super_enum.py
clark/super_json.py
clark/super_pidfile.py
clark/super_thread.py
clark.egg-info/PKG-INFO
clark.egg-info/SOURCES.txt
clark.egg-info/dependency_links.txt
clark.egg-info/not-zip-safe
clark.egg-info/requires.txt
clark.egg-info/top_level.txt