Metadata-Version: 1.1
Name: clark
Version: 0.1.0
Summary: Utility library.
Home-page: http://github.com/carlsverre/clark
Author: Carl Sverre
Author-email: accounts@carlsverre.com
License: LICENSE.txt
Platform: UNKNOWN
Classifier: License :: OSI Approved :: MIT License
Classifier: Programming Language :: Python :: 2.7
